{
  "player_id": 8476438,
  "player_name": "Brandon Saad",
  "team_abbrev": "STL",
  "goals": 13,
  "xg": 18.6,
  "gax": -5.6,
  "shots": 198,
  "sh_vs_expected": 0.7,
  "seasons": [
    {
      "season": "2018",
      "sh_vs_expected": 0.96
    },
    {
      "season": "2019",
      "sh_vs_expected": 1.01
    },
    {
      "season": "2020",
      "sh_vs_expected": 1.88
    },
    {
      "season": "2021",
      "sh_vs_expected": 1.08
    },
    {
      "season": "2022",
      "sh_vs_expected": 1.17
    },
    {
      "season": "2023",
      "sh_vs_expected": 1.38
    },
    {
      "season": "2024",
      "sh_vs_expected": 0.7
    },
    {
      "season": "2025",
      "sh_vs_expected": 0.34
    }
  ],
  "verdict": "Career average 6% above expected \u2014 watch for regression.",
  "injury_status": "HEALTHY"
}