{
  "player_id": 8476902,
  "player_name": "Esa Lindell",
  "team_abbrev": "DAL",
  "goals": 6,
  "xg": 8.0,
  "gax": -2.0,
  "shots": 175,
  "sh_vs_expected": 0.75,
  "hd_shot_pct": 6.3,
  "rebound_rate": 4.6,
  "rush_rate": 4.0,
  "position": "D",
  "seasons": [
    {
      "season": "2018",
      "goals": 12,
      "xg": 8.1,
      "gax": 3.9,
      "shots": 197,
      "sh_vs_expected": 1.48,
      "hd_shot_pct": 12.7,
      "rebound_rate": 3.0,
      "rush_rate": 0
    },
    {
      "season": "2019",
      "goals": 4,
      "xg": 7.4,
      "gax": -3.4,
      "shots": 183,
      "sh_vs_expected": 0.54,
      "hd_shot_pct": 13.1,
      "rebound_rate": 3.8,
      "rush_rate": 0
    },
    {
      "season": "2020",
      "goals": 5,
      "xg": 3.8,
      "gax": 1.2,
      "shots": 137,
      "sh_vs_expected": 1.32,
      "hd_shot_pct": 10.2,
      "rebound_rate": 4.4,
      "rush_rate": 0
    },
    {
      "season": "2021",
      "goals": 4,
      "xg": 5.4,
      "gax": -1.4,
      "shots": 179,
      "sh_vs_expected": 0.74,
      "hd_shot_pct": 9.5,
      "rebound_rate": 2.2,
      "rush_rate": 0
    },
    {
      "season": "2022",
      "goals": 8,
      "xg": 7.4,
      "gax": 0.6,
      "shots": 185,
      "sh_vs_expected": 1.08,
      "hd_shot_pct": 16.2,
      "rebound_rate": 2.7,
      "rush_rate": 0
    },
    {
      "season": "2023",
      "goals": 8,
      "xg": 7.8,
      "gax": 0.2,
      "shots": 203,
      "sh_vs_expected": 1.02,
      "hd_shot_pct": 8.9,
      "rebound_rate": 4.9,
      "rush_rate": 0
    },
    {
      "season": "2024",
      "goals": 6,
      "xg": 8.0,
      "gax": -2.0,
      "shots": 175,
      "sh_vs_expected": 0.75,
      "hd_shot_pct": 6.3,
      "rebound_rate": 4.6,
      "rush_rate": 0
    },
    {
      "season": "2025",
      "goals": 6,
      "xg": 7.1,
      "gax": -1.1,
      "shots": 130,
      "sh_vs_expected": 0.84,
      "hd_shot_pct": 16.2,
      "rebound_rate": 5.4,
      "rush_rate": 4.0
    }
  ],
  "verdict": "Career average 3% below expected \u2014 due for improvement.",
  "injury_status": "HEALTHY",
  "tracking": {
    "player_id": 8476902,
    "max_speed_mph": 21.75,
    "max_speed_pct": 55.4,
    "shot_speed_mph": 86.18,
    "shot_speed_pct": 22.1,
    "oz_pct": 39.0,
    "oz_percentile": 9.9,
    "distance_mi": 230.6,
    "distance_pct": 83.7
  },
  "faceoffs": null
}