{
  "player_id": 8481542,
  "player_name": "Moritz Seider",
  "team_abbrev": "DET",
  "goals": 8,
  "xg": 9.7,
  "gax": -1.7,
  "shots": 257,
  "sh_vs_expected": 0.83,
  "hd_shot_pct": 8.2,
  "rebound_rate": 3.1,
  "rush_rate": 2.1,
  "position": "D",
  "seasons": [
    {
      "season": "2021",
      "goals": 7,
      "xg": 9.0,
      "gax": -2.0,
      "shots": 246,
      "sh_vs_expected": 0.78,
      "hd_shot_pct": 7.3,
      "rebound_rate": 2.0,
      "rush_rate": 0
    },
    {
      "season": "2022",
      "goals": 5,
      "xg": 5.1,
      "gax": -0.1,
      "shots": 201,
      "sh_vs_expected": 0.98,
      "hd_shot_pct": 3.5,
      "rebound_rate": 1.0,
      "rush_rate": 0
    },
    {
      "season": "2023",
      "goals": 9,
      "xg": 6.8,
      "gax": 2.2,
      "shots": 192,
      "sh_vs_expected": 1.33,
      "hd_shot_pct": 7.3,
      "rebound_rate": 2.6,
      "rush_rate": 0
    },
    {
      "season": "2024",
      "goals": 8,
      "xg": 9.7,
      "gax": -1.7,
      "shots": 257,
      "sh_vs_expected": 0.83,
      "hd_shot_pct": 8.2,
      "rebound_rate": 3.1,
      "rush_rate": 0
    },
    {
      "season": "2025",
      "goals": 10,
      "xg": 7.5,
      "gax": 2.5,
      "shots": 285,
      "sh_vs_expected": 1.34,
      "hd_shot_pct": 4.9,
      "rebound_rate": 2.1,
      "rush_rate": 2.1
    }
  ],
  "verdict": "Career average 5% above expected \u2014 watch for regression.",
  "injury_status": "HEALTHY",
  "tracking": {
    "player_id": 8481542,
    "max_speed_mph": 22.88,
    "max_speed_pct": 90.6,
    "shot_speed_mph": 95.54,
    "shot_speed_pct": 81.4,
    "oz_pct": 42.9,
    "oz_percentile": 70.0,
    "distance_mi": 291.3,
    "distance_pct": 99.1
  },
  "faceoffs": null
}