{
  "player_id": 8482176,
  "player_name": "Wyatt Kaiser",
  "team_abbrev": "CHI",
  "goals": 4,
  "xg": 2.1,
  "gax": 1.9,
  "shots": 91,
  "sh_vs_expected": 1.93,
  "position": "D",
  "seasons": [
    {
      "season": "2022",
      "sh_vs_expected": 1.0
    },
    {
      "season": "2023",
      "sh_vs_expected": 1.0
    },
    {
      "season": "2024",
      "sh_vs_expected": 1.93
    },
    {
      "season": "2025",
      "sh_vs_expected": 1.5
    }
  ],
  "verdict": "Career average 36% above expected \u2014 watch for regression.",
  "injury_status": "HEALTHY"
}